setup.py
commonn.egg-info/PKG-INFO
commonn.egg-info/SOURCES.txt
commonn.egg-info/dependency_links.txt
commonn.egg-info/requires.txt
commonn.egg-info/top_level.txt
commonn/lib/__init__.py
commonn/lib/api.py
commonn/lib/newReport.py
commonn/lib/parsley.py
commonn/lib/readexcel.py
commonn/lib/sendmail.py
commonn/lib/utility.py
commonn/lib/writeexcel.py
commonn/package/HTMLTestRunner.py
commonn/package/__init__.py