Metadata-Version: 1.0
Name: commonn
Version: 6.0.0
Summary: commonn
Home-page: UNKNOWN
Author: cxx
Author-email: cuixiaoxia@chinasofti.com
License: UNKNOWN
Platform: UNKNOWN
